bioimageio/engine/__init__.py
bioimageio/engine/__main__.py
bioimageio/engine/app_loader.py
bioimageio/engine/ray_app_loader.py
bioimageio/engine/ray_app_manager.py
bioimageio/engine/apps/__init__.py
bioimageio/engine/apps/cellpose/README.md
bioimageio/engine/apps/cellpose/main.py
bioimageio/engine/apps/cellpose/manifest.yaml
bioimageio/engine/apps/cellpose/cellpose-predict/config.pbtxt
bioimageio/engine/apps/cellpose/cellpose-predict/1/model.py
bioimageio/engine/apps/cellpose/cellpose-predict/1/pyodide_test.py
bioimageio/engine/apps/cellpose/cellpose-train/config.pbtxt
bioimageio/engine/apps/cellpose/cellpose-train/1/build_bioimageio_package.py
bioimageio/engine/apps/cellpose/cellpose-train/1/interactive_cellpose.py
bioimageio/engine/apps/cellpose/cellpose-train/1/model.py
bioimageio/engine/apps/cellpose/cellpose-train/1/predict.py
bioimageio/engine/apps/cellpose/cellpose-train/1/test_cellpose_train.py
bioimageio/engine/apps/cellpose/cellpose-train/1/test_native.py
bioimageio/engine/apps/cellpose/cellpose-train/1/test_triton.py
bioimageio/engine/apps/imagej/main.py
bioimageio/engine/apps/imagej/run_imagej.py
bioimageio/engine/ray_apps/__init__.py
bioimageio/engine/ray_apps/cellpose/__init__.py
bioimageio/engine/ray_apps/cellpose/manifest.yaml
bioimageio/engine/ray_apps/micro_sam/__init__.py
bioimageio/engine/ray_apps/micro_sam/manifest.yaml
bioimageio/engine/ray_apps/translator/manifest.yaml
bioimageio/engine/ray_apps/translator/translator.py
bioimageio.engine-0.1.3.dist-info/LICENSE
bioimageio.engine-0.1.3.dist-info/METADATA
bioimageio.engine-0.1.3.dist-info/WHEEL
bioimageio.engine-0.1.3.dist-info/top_level.txt
bioimageio.engine-0.1.3.dist-info/RECORD
